docs/conf.py
docs/ext/link_tf_api.py
docs/ext/link_tf_api_test.py
examples/functional_mlp_mnist.py
examples/simple_mnist.py
examples/simple_mnist_test.py
sonnet/__init__.py
sonnet/distribute.py
sonnet/functional.py
sonnet/initializers.py
sonnet/mixed_precision.py
sonnet/optimizers.py
sonnet/pad.py
sonnet/regularizers.py
sonnet/nets/__init__.py
sonnet/nets/resnet.py
sonnet/src/__init__.py
sonnet/src/axis_norm.py
sonnet/src/axis_norm_test.py
sonnet/src/base.py
sonnet/src/base_test.py
sonnet/src/batch_apply.py
sonnet/src/batch_apply_test.py
sonnet/src/batch_norm.py
sonnet/src/batch_norm_test.py
sonnet/src/bias.py
sonnet/src/bias_test.py
sonnet/src/build.py
sonnet/src/build_test.py
sonnet/src/conv.py
sonnet/src/conv_test.py
sonnet/src/conv_transpose.py
sonnet/src/conv_transpose_test.py
sonnet/src/custom_getter.py
sonnet/src/custom_getter_test.py
sonnet/src/deferred.py
sonnet/src/deferred_test.py
sonnet/src/depthwise_conv.py
sonnet/src/depthwise_conv_test.py
sonnet/src/dropout.py
sonnet/src/dropout_test.py
sonnet/src/embed.py
sonnet/src/embed_test.py
sonnet/src/group_norm.py
sonnet/src/group_norm_test.py
sonnet/src/initializers.py
sonnet/src/initializers_test.py
sonnet/src/leaky_clip_by_value.py
sonnet/src/leaky_clip_by_value_test.py
sonnet/src/linear.py
sonnet/src/linear_test.py
sonnet/src/metrics.py
sonnet/src/metrics_test.py
sonnet/src/mixed_precision.py
sonnet/src/mixed_precision_test.py
sonnet/src/moving_averages.py
sonnet/src/moving_averages_test.py
sonnet/src/once.py
sonnet/src/once_test.py
sonnet/src/pad.py
sonnet/src/pad_test.py
sonnet/src/parallel_linear.py
sonnet/src/parallel_linear_test.py
sonnet/src/recurrent.py
sonnet/src/recurrent_test.py
sonnet/src/regularizers.py
sonnet/src/regularizers_test.py
sonnet/src/reshape.py
sonnet/src/reshape_test.py
sonnet/src/scale_gradient.py
sonnet/src/scale_gradient_test.py
sonnet/src/sequential.py
sonnet/src/sequential_test.py
sonnet/src/test_utils.py
sonnet/src/types.py
sonnet/src/utils.py
sonnet/src/utils_test.py
dm_sonnet-2.0.2.dist-info/LICENSE
dm_sonnet-2.0.2.dist-info/METADATA
dm_sonnet-2.0.2.dist-info/WHEEL
dm_sonnet-2.0.2.dist-info/top_level.txt
dm_sonnet-2.0.2.dist-info/RECORD
