Metadata-Version: 2.1
Name: dm-sonnet
Version: 2.0.2
Summary: Sonnet is a library for building neural networks in TensorFlow.
Home-page: https://github.com/deepmind/sonnet
Author: DeepMind
Author-email: sonnet-dev-os@google.com
License: Apache 2.0
Classifier: Development Status :: 3 - Alpha
Classifier: Intended Audience :: Developers
Classifier: Intended Audience :: Education
Classifier: Intended Audience :: Science/Research
Classifier: License :: OSI Approved :: Apache Software License
Classifier: Programming Language :: Python :: 3
Classifier: Programming Language :: Python :: 3.8
Classifier: Programming Language :: Python :: 3.9
Classifier: Programming Language :: Python :: 3.10
Classifier: Topic :: Scientific/Engineering :: Mathematics
Classifier: Topic :: Software Development :: Libraries :: Python Modules
Classifier: Topic :: Software Development :: Libraries
License-File: LICENSE
Requires-Dist: absl-py >=0.7.1
Requires-Dist: dm-tree >=0.1.1
Requires-Dist: numpy >=1.16.3
Requires-Dist: tabulate >=0.7.5
Requires-Dist: wrapt >=1.11.1
Provides-Extra: tensorflow
Requires-Dist: tensorflow >=2 ; extra == 'tensorflow'
Provides-Extra: tensorflow_with_gpu
Requires-Dist: tensorflow-gpu >=2 ; extra == 'tensorflow_with_gpu'
